hg2_item_parser/__init__.py
hg2_item_parser/__main__.py
hg2_item_parser/cli.py
hg2_item_parser/data_loader.py
hg2_item_parser/enums.py
hg2_item_parser/exceptions.py
hg2_item_parser/info_parser.py
hg2_item_parser/item_parser.py
hg2_item_parser/models.py
hg2_item_parser/property_parser.py
hg2_item_parser/skill_parser.py
hg2_item_parser/text_parser.py
hg2_item_parser/tsvreader.py
hg2_item_parser/unificator.py
hg2_item_parser/resources/TextMap_aio.tsv
hg2_item_parser-0.7.2.dist-info/METADATA
hg2_item_parser-0.7.2.dist-info/WHEEL
hg2_item_parser-0.7.2.dist-info/entry_points.txt
hg2_item_parser-0.7.2.dist-info/licenses/LICENSE
hg2_item_parser-0.7.2.dist-info/RECORD
