Metadata-Version: 2.3
Name: hg2-item-parser
Version: 0.7.2
Summary: Python package for parsing Houkai Gakuen 2 items data
Requires-Python: <4.0,>=3.12
Requires-Dist: requests<3.0.0,>=2.32.3
Requires-Dist: tqdm<5.0.0,>=4.66.6
Requires-Dist: typer<1.0.0,>=0.12.5
